skopeo.py
skopeo_bin-1.0.3.data/data/lib/skopeo_darwin
skopeo_bin-1.0.3.data/data/lib/skopeo_linux
skopeo_bin-1.0.3.dist-info/LICENSE
skopeo_bin-1.0.3.dist-info/METADATA
skopeo_bin-1.0.3.dist-info/WHEEL
skopeo_bin-1.0.3.dist-info/entry_points.txt
skopeo_bin-1.0.3.dist-info/top_level.txt
skopeo_bin-1.0.3.dist-info/RECORD
