Metadata-Version: 2.1
Name: skopeo-bin
Version: 1.0.3
Summary: UNKNOWN
Home-page: https://github.com/epiphany-platform/skopeo-bin
Author: Epiphany Team
Author-email: 
License: Apache License Version 2.0
Platform: UNKNOWN
